source_coop_mcp/__init__.py
source_coop_mcp/server.py
source_coop_mcp-0.2.6.dist-info/METADATA
source_coop_mcp-0.2.6.dist-info/WHEEL
source_coop_mcp-0.2.6.dist-info/entry_points.txt
source_coop_mcp-0.2.6.dist-info/RECORD
