Metadata-Version: 2.4
Name: source-coop-mcp
Version: 0.2.6
Summary: MCP server for Source Cooperative auto-discovery and data exploration
Project-URL: Homepage, https://github.com/yharby/source-coop-mcp
Project-URL: Repository, https://github.com/yharby/source-coop-mcp
Project-URL: Documentation, https://github.com/yharby/source-coop-mcp#readme
Project-URL: Issues, https://github.com/yharby/source-coop-mcp/issues
Project-URL: Changelog, https://github.com/yharby/source-coop-mcp/blob/main/CHANGELOG.md
Author-email: yharby <me@youssefharby.com>
License: MIT
Keywords: geospatial,mcp,model-context-protocol,object-storage,s3,source-cooperative
Classifier: Development Status :: 4 - Beta
Classifier: Intended Audience :: Developers
Classifier: License :: OSI Approved :: MIT License
Classifier: Operating System :: OS Independent
Classifier: Programming Language :: Python :: 3.11
Classifier: Programming Language :: Python :: 3.12
Classifier: Programming Language :: Python :: 3.13
Classifier: Topic :: Scientific/Engineering :: GIS
Classifier: Topic :: Software Development :: Libraries :: Python Modules
Classifier: Typing :: Typed
Requires-Python: >=3.11
Requires-Dist: fastmcp>=2.13.0
Requires-Dist: httpx>=0.28.1
Requires-Dist: obstore>=0.8.2
Provides-Extra: dev
Requires-Dist: pre-commit>=4.3.0; extra == 'dev'
Requires-Dist: pytest-asyncio>=1.2.0; extra == 'dev'
Requires-Dist: pytest>=8.4.2; extra == 'dev'
Requires-Dist: ruff>=0.14.4; extra == 'dev'
